pdf_highlight_extractor/__init__.py
pdf_highlight_extractor/reader.py
pdf_highlight_extractor-0.1.2.dist-info/licenses/LICENSE
pdf_highlight_extractor-0.1.2.dist-info/METADATA
pdf_highlight_extractor-0.1.2.dist-info/WHEEL
pdf_highlight_extractor-0.1.2.dist-info/top_level.txt
pdf_highlight_extractor-0.1.2.dist-info/RECORD
